README.rst
setup.py
rqpop/__init__.py
rqpop/cli.py
rqpop/qpopulator.py
rqpop.egg-info/PKG-INFO
rqpop.egg-info/SOURCES.txt
rqpop.egg-info/dependency_links.txt
rqpop.egg-info/entry_points.txt
rqpop.egg-info/requires.txt
rqpop.egg-info/top_level.txt