Metadata-Version: 1.1
Name: rqpop
Version: 0.0.2
Summary: A package to enqueue a variable number of jobs with variably distributed TIME x CPU "areas"
Home-page: https://github.com/salbrandi/rqpop
Author: Salvador Brandi
Author-email: salbrandi@gmail.com
License: UNKNOWN
Download-URL: https://github.com/salbrandi/rqpop/archive/0.1.tar.gz
Keywords: rq queue distribution scipy tetris-queue tetris test loads populate population job enqueue backfill
Platform: UNKNOWN
Classifier: Development Status :: 3 - Alpha
Classifier: Programming Language :: Python :: 3 :: Only
